conda_pack/__init__.py
conda_pack/_progress.py
conda_pack/_version.py
conda_pack/cli.py
conda_pack/compat.py
conda_pack/core.py
conda_pack/formats.py
conda_pack/prefixes.py
conda_pack/scripts/posix/activate
conda_pack/scripts/posix/deactivate
conda_pack/scripts/posix/parcel
conda_pack/scripts/windows/activate.bat
conda_pack/scripts/windows/deactivate.bat
conda_pack-0.7.1.dist-info/LICENSE.txt
conda_pack-0.7.1.dist-info/METADATA
conda_pack-0.7.1.dist-info/WHEEL
conda_pack-0.7.1.dist-info/entry_points.txt
conda_pack-0.7.1.dist-info/top_level.txt
conda_pack-0.7.1.dist-info/RECORD
