Metadata-Version: 2.1
Name: conda-pack
Version: 0.7.1
Summary: Package conda environments for redistribution
Home-page: https://conda.github.io/conda-pack/
Maintainer: Jim Crist
Maintainer-email: jiminy.crist@gmail.com
License: BSD
Project-URL: Source Code, https://github.com/conda/conda-pack
Keywords: conda packaging
Classifier: Development Status :: 4 - Beta
Classifier: License :: OSI Approved :: BSD License
Classifier: Programming Language :: Python :: 3.7
Classifier: Programming Language :: Python :: 3.8
Classifier: Programming Language :: Python :: 3.9
Classifier: Programming Language :: Python :: 3.10
Classifier: Topic :: System :: Archiving :: Packaging
Classifier: Topic :: System :: Software Distribution
Classifier: Topic :: Software Development :: Build Tools
Requires-Python: >=3.7
License-File: LICENSE.txt
